{
  local_meter_id: "1f416c1b-28da-4577-a5e0-d0be526fc5c5",
  device_id: "54919617",
  device_type: "HCA",
  manufacturer: "EFE",
  frame_type: "SND_NR",
  version: "31h",
  access_number: 26,
  status: "00h",
  encryption: 5,
  parsed_data: {
    "Frame Type": "SND_NR",
    Manufacturer: "EFE",
    ID: "54919617",
    Version: "31h",
    "Device Type": "HCA",
    "TPL-Config": "Response,Uplink,TPL=S,M-Bus",
    "Access Number": 26,
    Status: "00h",
    Encryption: 5,
    "IV,0,0,0,,Date/Time": "26.02.2026 09:01 invalid 0 summer time 0",
    "IV,0,0,0,,Units HCA": 17,
    "IV,1,0,0,,Date": "31.12.2025", // <- dec
    "IV,1,0,0,,Units HCA": 5, // <- dec
    "IV,2,0,0,,Date": "30.11.2024",
    "IV,2,0,0,,Units HCA": 0,
    "IV,3,0,0,,Units HCA": 0,
    "IV,4,0,0,,Units HCA": 0,
    "IV,5,0,0,,Units HCA": 0,
    "IV,6,0,0,,Units HCA": 0,
    "IV,7,0,0,,Units HCA": 0,
    "IV,8,0,0,,Units HCA": 0,
    "IV,9,0,0,,Units HCA": 0,
    "IV,10,0,0,,Units HCA": 0,
    "IV,11,0,0,,Units HCA": 0,
    "IV,12,0,0,,Units HCA": 0,
    "IV,13,0,0,,Units HCA": 0,
    "IV,14,0,0,,Units HCA": 0,
    "IV,15,0,0,,Units HCA": 0,
    "IV,16,0,0,,Units HCA": 0,
    "IV,17,0,0,,Units HCA": 0,
    "IV,18,0,0,,Units HCA": 0,
    "IV,19,0,0,,Units HCA": 0,
    "IV,20,0,0,,Units HCA": 0,
    "IV,21,0,0,,Units HCA": 0,
    "IV,22,0,0,,Units HCA": 0,
    "IV,23,0,0,,Units HCA": 0,
    "IV,24,0,0,,Units HCA": 0,
    "IV,25,0,0,,Units HCA": 0,
    "IV,26,0,0,,Units HCA": 0,
    "IV,27,0,0,,Units HCA": 0,
    "IV,28,0,0,,Units HCA": 5,
    "IV,29,0,0,,Units HCA": -2,
    "IV,30,0,0,,Units HCA": 5,
    "IV,31,0,0,,Units HCA": 5,
    "ErrorV,0,0,0,,ManufacturerSpecific": 0,
    "ErrorV,0,0,0,,Date/Time": "00.00.2000 00:00 invalid 0 summer time 0",
  },
  date_only: "2026-02-26",
} 
